vimdecrypt.py
vimdecrypt-2.1.0.dist-info/licenses/LICENSE
vimdecrypt-2.1.0.dist-info/METADATA
vimdecrypt-2.1.0.dist-info/WHEEL
vimdecrypt-2.1.0.dist-info/entry_points.txt
vimdecrypt-2.1.0.dist-info/top_level.txt
vimdecrypt-2.1.0.dist-info/RECORD
