Metadata-Version: 2.4
Name: vimdecrypt
Version: 2.1.0
Author: Gertjan van Zwieten
Requires-Python: >=3.0
License-File: LICENSE
Requires-Dist: blowfish
Dynamic: license-file
